hpssa/__init__.py
hpssa/_cli.py
hpssa/hpssa.py
python_hpssa-0.0.14.dist-info/DESCRIPTION.rst
python_hpssa-0.0.14.dist-info/METADATA
python_hpssa-0.0.14.dist-info/RECORD
python_hpssa-0.0.14.dist-info/WHEEL
python_hpssa-0.0.14.dist-info/metadata.json
python_hpssa-0.0.14.dist-info/top_level.txt
