Metadata-Version: 2.0
Name: python-hpssa
Version: 0.0.14
Summary: Python module for working with HP Smart Array controllers
Home-page: UNKNOWN
Author: Jared Rodriguez
Author-email: jared@blacknode.net
License: Apache-2.0
Platform: UNKNOWN
Requires-Dist: python-size
